avsos/__init__.py
avsos/config.ini
avsos/config.py
avsos/encryption.py
avsos/main.py
avsos/osint.py
avsos/portscan.py
avsos/service-names-port-numbers.csv
avsos/setup.py
avsos/start_zap.py
avsos/utils.py
avsos/zapscan.py
avsos-0.0.9.dist-info/METADATA
avsos-0.0.9.dist-info/WHEEL
avsos-0.0.9.dist-info/entry_points.txt
avsos-0.0.9.dist-info/top_level.txt
avsos-0.0.9.dist-info/RECORD
